crml_engine/__init__.py
crml_engine/cli.py
crml_engine/controls.py
crml_engine/copula.py
crml_engine/explainer.py
crml_engine/runtime.py
crml_engine/models/__init__.py
crml_engine/models/constants.py
crml_engine/models/fx_model.py
crml_engine/models/result_model.py
crml_engine/pipeline/__init__.py
crml_engine/pipeline/portfolio_planner.py
crml_engine/simulation/__init__.py
crml_engine/simulation/engine.py
crml_engine/simulation/frequency.py
crml_engine/simulation/severity.py
crml_engine/simulation/utils.py
crml_engine-1.2.0.dist-info/licenses/LICENSE
crml_engine-1.2.0.dist-info/METADATA
crml_engine-1.2.0.dist-info/WHEEL
crml_engine-1.2.0.dist-info/entry_points.txt
crml_engine-1.2.0.dist-info/top_level.txt
crml_engine-1.2.0.dist-info/RECORD
