Metadata-Version: 2.4
Name: crml-engine
Version: 1.2.0
Summary: CRML reference engine (simulation/runtime)
Author: Zeron Research Labs
License: MIT License
Project-URL: Homepage, https://github.com/Faux16/crml
Project-URL: Repository, https://github.com/Faux16/crml
Project-URL: Documentation, https://faux16.github.io/crml/
Classifier: Programming Language :: Python :: 3
Classifier: License :: OSI Approved :: MIT License
Classifier: Operating System :: OS Independent
Requires-Python: >=3.9
License-File: LICENSE
Requires-Dist: crml-lang>=1.2.0
Requires-Dist: numpy
Requires-Dist: scipy
Requires-Dist: pydantic
Requires-Dist: pyyaml
Provides-Extra: dev
Requires-Dist: pytest; extra == "dev"
Dynamic: license-file
